frd/__init__.py
frd/command.py
frd/crawler.py
frd/daemon.py
frd/http.py
frd/path.py
frd/sqlite.py
frd/t.py
frd/validator.py
frd/webdriver.py
frd/db/__init__.py
frd/db/es.py
frd/db/jsondb.py
frd/db/mysql.py
frd/db/python2_mysql.py
frd/db/simple.py
frd/db/sqlite.py
frd/functions/__init__.py
frd/functions/base.py
frd/functions/file.py
frd/functions/textfile.py
frd/pygame/__init__.py
frd/pygame/game.py
frd/qt/__init__.py
frd/qt/dialog.py
frd/qt/func.py
frd/qt/message.py
frd/qt/t.py
frd/qt/template.py
frd-0.0.10.dist-info/DESCRIPTION.rst
frd-0.0.10.dist-info/METADATA
frd-0.0.10.dist-info/RECORD
frd-0.0.10.dist-info/WHEEL
frd-0.0.10.dist-info/metadata.json
frd-0.0.10.dist-info/top_level.txt
