Metadata-Version: 2.0
Name: frd
Version: 0.0.10
Summary: Frd Python Lib
Home-page: https://frd.life
Author: fred
Author-email: iamlosing02@gmail.com
License: MIT
Keywords: frd
Platform: UNKNOWN
Classifier: Topic :: Software Development :: Libraries :: Python Modules
Classifier: License :: OSI Approved :: MIT License
Classifier: Programming Language :: Python :: 3
Classifier: Programming Language :: Python :: 3.4
Requires-Dist: termcolor
Requires-Dist: chardet
Requires-Dist: requests
